{
  "_id": "page.grave_digger.no_documentation",
  "_type": "page.singlequestion",
  "components": [
    {
      "_id": "page.grave_digger.no_documentation.textarea",
      "_isa": "textarea.no-documentation",
      "_type": "textarea",
      "errors": {
        "required": {
          "any": "Enter why you do not have receipts"
        }
      },
      "label": "Tell us why you don’t have receipts for the fees charged by a third-party grave digger",
      "name": "no_documentation_grave_digger",
      "show": {
        "identifier": "receipt_grave_digger",
        "operator": "is",
        "value": "no"
      }
    }
  ],
  "url": "no-documentation"
}